{"files":{"index-2.html":{"frameworks":["consult","pg.asset.manager","pg.project.items","pg.code-validator","pg.insight.events","pg.css.grid","pg.image.overlay","pg.fontawesome","bs3.4.1","pg.html","pg.components"],"last_page_width":1280},"index.html":{"frameworks":["consult","pg.code-validator","pg.insight.events","pg.asset.manager","pg.project.items","pg.css.grid","pg.image.overlay","pg.fontawesome","bs3.4.1","pg.html","pg.components"],"last_page_width":1024},"about.html":{"frameworks":["consult","pg.insight.events","pg.asset.manager","pg.project.items","pg.css.grid","pg.fontawesome","pg.code-validator","pg.image.overlay","bs3.4.1","pg.html","pg.components"],"last_page_width":1024}},"breakpoints":["460px","480px","768px","992px","1200px"],"frameworks":["consult","pg.code-validator","pg.insight.events","pg.asset.manager","pg.project.items","pg.css.grid","pg.image.overlay","pg.fontawesome","bs3.4.1","pg.html","pg.components"],"file-picker-copy-folder":"/home/higaki/Público/Sites/consult/img"}